{
  "header": {
    "orderNumber": "ORD-2024-78523",
    "orderDate": "12/15/2024",
    "orderTime": "14:35:22",
    "channel": "WEB",
    "storeCode": "STORE-001",
    "register": "T-15",
    "associateId": "EMP-4521",
    "status": "SHIP",
    "priorityCode": "Y",
    "giftOrder": "N",
    "orderNotes": "  Please leave at back door.  Handle with care.  "
  },
  "customer": {
    "customerId": "CUST-98765",
    "customerType": "P",
    "firstName": "JENNIFER",
    "middleName": "MARIE",
    "lastName": "SMITH-JOHNSON",
    "suffix": "III",
    "email": "  JENNIFER.SMITH@EXAMPLE.COM  ",
    "primaryPhone": "2125551234",
    "secondaryPhone": "9175559876",
    "phoneType": "M",
    "birthDate": "06/15/1985",
    "gender": "F",
    "ssn": "123-45-6789",
    "taxExempt": "N",
    "loyaltyNumber": "LYL-456789",
    "loyaltyTier": "G",
    "loyaltyPoints": 15750,
    "lifetimeSpend": 28945.67,
    "accountBalance": -125.50,
    "creditLimit": 5000.00,
    "preferredContact": "E",
    "marketingOptIn": "Y",
    "smsOptIn": "N",
    "language": "EN",
    "currency": "USD"
  },
  "billTo": {
    "line1": "123 MAIN STREET",
    "line2": "APT 4B",
    "line3": null,
    "city": "NEW YORK",
    "state": "NY",
    "zip": "10001",
    "country": "US",
    "validated": "Y",
    "residential": "Y"
  },
  "shipTo": {
    "line1": "456 OAK AVENUE",
    "line2": "SUITE 200",
    "line3": "BUILDING C",
    "city": "BROOKLYN",
    "state": "NY",
    "zip": "11201",
    "country": "US",
    "validated": "Y",
    "residential": "N",
    "instructions": "Ring bell twice"
  },
  "items": [
    {
      "lineNum": 1,
      "sku": "ELEC-TV-55-4K",
      "upc": "012345678901",
      "description": "55 INCH 4K SMART TV",
      "category": "ELEC",
      "subcategory": "TV",
      "brand": "SAMSONIC",
      "modelNumber": "SN-55X4K",
      "color": "BLACK",
      "size": null,
      "quantityOrdered": 1,
      "quantityShipped": 1,
      "quantityBackordered": 0,
      "unitPrice": 799.99,
      "unitCost": 450.00,
      "discountPercent": 10.00,
      "discountAmount": 80.00,
      "discountCode": "HOLIDAY2024",
      "lineTotal": 719.99,
      "taxable": "Y",
      "taxRate": 8.875,
      "taxAmount": 63.90,
      "weight": 45.5,
      "hazmat": "N",
      "giftWrap": "N",
      "giftMessage": null,
      "warrantyCode": "WARR-3YR-TV",
      "warrantyPrice": 99.99,
      "serialNumber": "SN-2024-78901",
      "shipDate": "12/16/2024",
      "trackingNumber": "1Z999AA10123456784",
      "carrier": "UPS",
      "fulfillmentStatus": "SHIPPED"
    },
    {
      "lineNum": 2,
      "sku": "ELEC-SOUND-BAR",
      "upc": "012345678902",
      "description": "WIRELESS SOUND BAR",
      "category": "ELEC",
      "subcategory": "AUDIO",
      "brand": "SAMSONIC",
      "modelNumber": "SN-SB500",
      "color": "BLACK",
      "size": null,
      "quantityOrdered": 1,
      "quantityShipped": 1,
      "quantityBackordered": 0,
      "unitPrice": 299.99,
      "unitCost": 150.00,
      "discountPercent": 15.00,
      "discountAmount": 45.00,
      "discountCode": "BUNDLE50",
      "lineTotal": 254.99,
      "taxable": "Y",
      "taxRate": 8.875,
      "taxAmount": 22.63,
      "weight": 12.3,
      "hazmat": "N",
      "giftWrap": "N",
      "giftMessage": null,
      "warrantyCode": null,
      "warrantyPrice": 0,
      "serialNumber": "SN-2024-78902",
      "shipDate": "12/16/2024",
      "trackingNumber": "1Z999AA10123456784",
      "carrier": "UPS",
      "fulfillmentStatus": "SHIPPED"
    },
    {
      "lineNum": 3,
      "sku": "CABLE-HDMI-6FT",
      "upc": "012345678903",
      "description": "PREMIUM HDMI CABLE 6FT",
      "category": "ACCS",
      "subcategory": "CABLES",
      "brand": "TECHCORD",
      "modelNumber": "TC-HDMI-6",
      "color": null,
      "size": "6FT",
      "quantityOrdered": 2,
      "quantityShipped": 2,
      "quantityBackordered": 0,
      "unitPrice": 24.99,
      "unitCost": 8.00,
      "discountPercent": 0,
      "discountAmount": 0,
      "discountCode": null,
      "lineTotal": 49.98,
      "taxable": "Y",
      "taxRate": 8.875,
      "taxAmount": 4.44,
      "weight": 0.5,
      "hazmat": "N",
      "giftWrap": "Y",
      "giftMessage": "Happy Holidays!",
      "warrantyCode": null,
      "warrantyPrice": 0,
      "serialNumber": null,
      "shipDate": "12/16/2024",
      "trackingNumber": "1Z999AA10123456785",
      "carrier": "UPS",
      "fulfillmentStatus": "SHIPPED"
    }
  ],
  "payments": [
    {
      "sequence": 1,
      "method": "CC",
      "cardType": "VISA",
      "lastFour": "4242",
      "expiration": "12/26",
      "cardHolder": "JENNIFER M SMITH-JOHNSON",
      "amount": 1000.00,
      "authCode": "AUTH123456",
      "transactionId": "TXN-789456123",
      "avsResult": "Y",
      "cvvResult": "M"
    },
    {
      "sequence": 2,
      "method": "LOYALTY",
      "cardType": null,
      "lastFour": null,
      "expiration": null,
      "cardHolder": null,
      "amount": 157.50,
      "authCode": null,
      "transactionId": "LYL-REDEEM-456",
      "avsResult": null,
      "cvvResult": null
    }
  ],
  "totals": {
    "merchandiseTotal": 1024.96,
    "discountTotal": 125.00,
    "subtotal": 1024.96,
    "taxTotal": 90.97,
    "shippingCost": 15.99,
    "shippingDiscount": 15.99,
    "giftWrapTotal": 5.99,
    "warrantyTotal": 99.99,
    "grandTotal": 1215.92,
    "amountPaid": 1157.50,
    "balanceDue": 58.42
  },
  "shipping": {
    "method": "GROUND",
    "carrier": "UPS",
    "speed": "5-7 BUSINESS DAYS",
    "estimatedDelivery": "12/22/2024",
    "signatureRequired": "Y",
    "insuranceAmount": 1200.00,
    "packageCount": 2,
    "totalWeight": 58.3,
    "trackingNumbers": ["1Z999AA10123456784", "1Z999AA10123456785"]
  },
  "promotions": [
    {
      "code": "HOLIDAY2024",
      "description": "Holiday 10% Off Electronics",
      "type": "PERCENT",
      "value": 10.00,
      "savings": 80.00
    },
    {
      "code": "BUNDLE50",
      "description": "Bundle Discount 15%",
      "type": "PERCENT",
      "value": 15.00,
      "savings": 45.00
    },
    {
      "code": "FREESHIP",
      "description": "Free Shipping Over $50",
      "type": "SHIPPING",
      "value": 100.00,
      "savings": 15.99
    }
  ],
  "audit": {
    "createdBy": "WEB_SERVICE",
    "createdAt": "12/15/2024 14:35:22",
    "modifiedBy": "SHIP_SERVICE",
    "modifiedAt": "12/16/2024 08:15:33",
    "version": 3,
    "source": "LEGACY_OMS"
  }
}
